mongo_simple_analytic/__about__.py
mongo_simple_analytic/__init__.py
mongo_simple_analytic-0.0.2.dist-info/METADATA
mongo_simple_analytic-0.0.2.dist-info/WHEEL
mongo_simple_analytic-0.0.2.dist-info/licenses/LICENSE.txt
mongo_simple_analytic-0.0.2.dist-info/RECORD
