Metadata-Version: 2.4
Name: mongo-simple-analytic
Version: 0.0.2
Project-URL: Documentation, https://github.com/haowu4/mongo-logger#readme
Project-URL: Issues, https://github.com/haowu4/mongo-logger/issues
Project-URL: Source, https://github.com/haowu4/mongo-logger
Author-email: haowu4 <haowu@dataset.sh>
License-Expression: MIT
License-File: LICENSE.txt
Classifier: Development Status :: 4 - Beta
Classifier: Programming Language :: Python
Classifier: Programming Language :: Python :: 3.8
Classifier: Programming Language :: Python :: 3.9
Classifier: Programming Language :: Python :: 3.10
Classifier: Programming Language :: Python :: 3.11
Classifier: Programming Language :: Python :: 3.12
Classifier: Programming Language :: Python :: Implementation :: CPython
Classifier: Programming Language :: Python :: Implementation :: PyPy
Requires-Python: >=3.8
Requires-Dist: pymongo
